ironic_hds-0.2.3.dist-info/DESCRIPTION.rst
ironic_hds-0.2.3.dist-info/METADATA
ironic_hds-0.2.3.dist-info/RECORD
ironic_hds-0.2.3.dist-info/WHEEL
ironic_hds-0.2.3.dist-info/entry_points.txt
ironic_hds-0.2.3.dist-info/metadata.json
ironic_hds-0.2.3.dist-info/pbr.json
ironic_hds-0.2.3.dist-info/top_level.txt
usr/lib/python2.7/site-packages/ironic_hds/__init__.py
usr/lib/python2.7/site-packages/ironic_hds/hds.py
usr/lib/python2.7/site-packages/ironic_hds/modules/__init__.py
usr/lib/python2.7/site-packages/ironic_hds/modules/client.py
usr/lib/python2.7/site-packages/ironic_hds/modules/common.py
usr/lib/python2.7/site-packages/ironic_hds/modules/management.py
usr/lib/python2.7/site-packages/ironic_hds/modules/power.py
