Metadata-Version: 2.0
Name: ironic-hds
Version: 0.2.3
Summary: OpenStack Ironic driver for Redfish/HDS systems
Home-page: https://github.com/hafe/ironic-hds
Author: Hans Feldt <hans.feldt@ericsson.com>
Author-email: isma.casti@gmail.com
License: UNKNOWN
Platform: UNKNOWN
Classifier: Environment :: OpenStack
Classifier: Intended Audience :: Information Technology
Classifier: Intended Audience :: System Administrators
Classifier: License :: OSI Approved :: Apache Software License
Classifier: Operating System :: POSIX :: Linux
Classifier: Programming Language :: Python
Classifier: Programming Language :: Python :: 2
Classifier: Programming Language :: Python :: 2.7
Requires-Python: >=2.7
